AUTHORS.md
CONTRIBUTING.md
HISTORY.md
LICENSE
MANIFEST.in
README.md
setup.cfg
setup.py
docs/Makefile
docs/authors.rst
docs/conf.py
docs/contributing.rst
docs/history.rst
docs/index.rst
docs/installation.rst
docs/make.bat
docs/readme.rst
docs/usage.rst
tests/__init__.py
tests/test_yaml_dump.py
yaml_dump/__init__.py
yaml_dump/cli.py
yaml_dump/yaml_dump.py
yaml_dump.egg-info/PKG-INFO
yaml_dump.egg-info/SOURCES.txt
yaml_dump.egg-info/dependency_links.txt
yaml_dump.egg-info/entry_points.txt
yaml_dump.egg-info/not-zip-safe
yaml_dump.egg-info/requires.txt
yaml_dump.egg-info/top_level.txt