Metadata-Version: 1.1
Name: yaml-dump
Version: 0.3.0
Summary: Sane default for YAML dump
Home-page: https://bitbucket.com/fingul/yaml_dump
Author: Fingul
Author-email: fingul@gmail.com
License: MIT license
Keywords: yaml_dump
Platform: UNKNOWN
Classifier: Development Status :: 2 - Pre-Alpha
Classifier: Intended Audience :: Developers
Classifier: License :: OSI Approved :: MIT License
Classifier: Natural Language :: English
Classifier: Programming Language :: Python :: 3.5
